qnit/__init__.py
qnit/data_types.py
qnit/errors.py
qnit/pint_units.txt
qnit/py.typed
qnit/quantity_types.py
qnit/tools.py
qnit/units_collections.py
qnit/units_types.py
qnit-0.5.0.dist-info/LICENSE
qnit-0.5.0.dist-info/METADATA
qnit-0.5.0.dist-info/WHEEL
qnit-0.5.0.dist-info/RECORD
