Metadata-Version: 2.1
Name: qnit
Version: 0.5.0
Summary: A Python library for object-oriented parameters, physical quantities and units with a strong support for typing.
Home-page: https://gitlab.com/c4dht/qnit
Author: Paul Kernstock
Author-email: paul.kernstock@posteo.de
Maintainer: Paul Kernstock
Maintainer-email: paul.kernstock@posteo.de
Requires-Python: >=3.9,<3.13
Classifier: Development Status :: 4 - Beta
Classifier: Framework :: Pytest
Classifier: Framework :: tox
Classifier: Intended Audience :: Science/Research
Classifier: License :: OSI Approved :: GNU Affero General Public License v3 or later (AGPLv3+)
Classifier: Programming Language :: Python :: 3
Classifier: Programming Language :: Python :: 3.9
Classifier: Programming Language :: Python :: 3.10
Classifier: Programming Language :: Python :: 3.11
Classifier: Programming Language :: Python :: 3.12
Classifier: Programming Language :: Python :: 3 :: Only
Classifier: Topic :: Scientific/Engineering
Classifier: Topic :: Scientific/Engineering :: Physics
Classifier: Typing :: Typed
Requires-Dist: numpy (>=1,<2)
Requires-Dist: pandas (>=2,<3)
Requires-Dist: pandas-stubs (>=2,<3)
Requires-Dist: pint[pandas] (>=0.22,<0.23)
Requires-Dist: scipy (>=1,<2)
Project-URL: Changelog, https://gitlab.com/c4dht/qnit/blob/main/CHANGELOG.md
Project-URL: Issues, https://gitlab.com/c4dht/qnit/issues
Project-URL: Repository, https://gitlab.com/c4dht/qnit
